{
  "_comment": "Stable DR-number ledger for rulebook-to-rulespeak. Auto-maintained; feed this file back in on the next build to keep rule numbers stable. Numbers in 'Retired' are tombstones and are never reissued. Hand-edit an Assignments number only to deliberately re-pin a rule.",
  "NextId": 78,
  "Assignments": {
    "Studies.TotalCases": 1,
    "Studies.CellCount": 2,
    "Treatments.TotalCases": 3,
    "Treatments.TotalSuccesses": 4,
    "Treatments.PooledSuccessRate": 5,
    "Strata.TotalCases": 6,
    "CaseCells.CellSuccessRate": 7,
    "CaseCells.TotalCasesForTreatment": 8,
    "CaseCells.TreatmentExposureFraction": 9,
    "StratumSummaries.StratumSuccesses": 10,
    "StratumSummaries.StratumCases": 11,
    "StratumSummaries.StratumSuccessRate": 12,
    "StratumSummaries.StratumSuccessesA": 13,
    "StratumSummaries.StratumCasesA": 14,
    "StratumSummaries.StratumRateA": 15,
    "StratumSummaries.StratumSuccessesB": 16,
    "StratumSummaries.StratumCasesB": 17,
    "StratumSummaries.StratumRateB": 18,
    "StratumSummaries.StratumWinner": 19,
    "StratumSummaries.StudyTotalCases": 20,
    "StratumSummaries.StratumTotalCases": 21,
    "StratumSummaries.StratumFraction": 22,
    "StratumSummaries.WeightedStratumRate": 23,
    "StratumSummaries.TreatmentACasesHere": 24,
    "StratumSummaries.TreatmentBCasesHere": 25,
    "StratumSummaries.TreatmentATotalCases": 26,
    "StratumSummaries.TreatmentBTotalCases": 27,
    "StratumSummaries.AllocationFractionA": 28,
    "StratumSummaries.AllocationFractionB": 29,
    "StratumSummaries.AllocationBias": 30,
    "StratumSummaries.StratumGap": 31,
    "StratumSummaries.WeightedStratumGap": 32,
    "ModelSummary.ReversalCount": 33,
    "ModelSummary.NonReversalCount": 34,
    "ModelSummary.StudyCount": 35,
    "ModelSummary.ExplainedCount": 36,
    "ModelSummary.ZeroStrengthCount": 37,
    "ModelSummary.PartialCount": 38,
    "ModelSummary.TotalParadoxStrength": 39,
    "ModelSummary.AvgParadoxStrength": 40,
    "ModelSummary.TypeACount": 41,
    "ModelSummary.TypeBCount": 42,
    "ModelSummary.TypeCCount": 43,
    "ModelSummary.TypeDCount": 44,
    "ModelSummary.TypeAFraction": 45,
    "ModelSummary.DistortionTaxonomyCoverage": 46,
    "StratumVariables.IsConfounder": 47,
    "TreatmentRankings.TotalCasesA": 48,
    "TreatmentRankings.TotalSuccessesA": 49,
    "TreatmentRankings.PooledRateA": 50,
    "TreatmentRankings.TotalCasesB": 51,
    "TreatmentRankings.TotalSuccessesB": 52,
    "TreatmentRankings.PooledRateB": 53,
    "TreatmentRankings.PooledWinner": 54,
    "TreatmentRankings.StratumCount": 55,
    "TreatmentRankings.StrataWonByA": 56,
    "TreatmentRankings.StrataWonByB": 57,
    "TreatmentRankings.PerStratumWinner": 58,
    "TreatmentRankings.IsReversal": 59,
    "TreatmentRankings.ConfoundersInStudy": 60,
    "TreatmentRankings.IsParadoxExplained": 61,
    "TreatmentRankings.PooledGap": 62,
    "TreatmentRankings.StrataWonByLoser": 63,
    "TreatmentRankings.ParadoxStrength": 64,
    "TreatmentRankings.PooledRateFromWeightsA": 65,
    "TreatmentRankings.PooledRateFromWeightsB": 66,
    "TreatmentRankings.ReversalIntensity": 67,
    "TreatmentRankings.ThresholdMargin": 68,
    "TreatmentRankings.SignedPooledGap": 69,
    "TreatmentRankings.WeightedStratumGapSum": 70,
    "TreatmentRankings.IsSignFlip": 71,
    "TreatmentRankings.AllocationDistortion": 72,
    "TreatmentRankings.DistortionType": 73,
    "TreatmentRankings.PolicyImplication": 74,
    "TreatmentRankings.IsReversal_v2": 75,
    "TreatmentRankings.DefinitionDelta": 76,
    "TreatmentRankings.StrictReversalSubtype": 77
  },
  "Retired": []
}
